kernel_server/__init__.py
kernel_server/_version.py
kernel_server/connect.py
kernel_server/message.py
kernel_server/server.py
kernel_server-0.0.5.dist-info/LICENSE
kernel_server-0.0.5.dist-info/METADATA
kernel_server-0.0.5.dist-info/WHEEL
kernel_server-0.0.5.dist-info/top_level.txt
kernel_server-0.0.5.dist-info/RECORD
